Metadata-Version: 1.1
Name: sourceparse
Version: 0.2.5
Summary: utility to inspect python source codes
Home-page: https://github.com/nlaurance/sourceparse
Author: Nicolas Laurance
Author-email: nicolas[dot]laurance[at]gmail[dot]com
License: MIT
Keywords: source code,analyzer
Platform: UNKNOWN
Classifier: Development Status :: 4 - Beta
Classifier: Topic :: Software Development :: Libraries :: Python Modules
Classifier: Intended Audience :: Developers
Classifier: Operating System :: OS Independent
Classifier: Programming Language :: Python
Classifier: License :: OSI Approved :: MIT License
